pyrrowhead/__init__.py
pyrrowhead/_setup.py
pyrrowhead/constants.py
pyrrowhead/main.py
pyrrowhead/types_.py
pyrrowhead/utils.py
pyrrowhead/certificate_generation/__init__.py
pyrrowhead/certificate_generation/lib_certs.sh
pyrrowhead/certificate_generation/mk_certs.sh
pyrrowhead/certificate_generation/rm_certs.sh
pyrrowhead/cloud/__init__.py
pyrrowhead/cloud/cli.py
pyrrowhead/cloud/client_add.py
pyrrowhead/cloud/configuration.py
pyrrowhead/cloud/create.py
pyrrowhead/cloud/file_generators.py
pyrrowhead/cloud/initialize_cloud.py
pyrrowhead/cloud/installation.py
pyrrowhead/cloud/start.py
pyrrowhead/cloud/stop.py
pyrrowhead/database_config/__init__.py
pyrrowhead/database_config/initSQL.sh
pyrrowhead/database_config/passwords.py
pyrrowhead/management/__init__.py
pyrrowhead/management/api.py
pyrrowhead/management/authorization.py
pyrrowhead/management/common.py
pyrrowhead/management/deviceregistry.py
pyrrowhead/management/orchestrator.py
pyrrowhead/management/serviceregistry.py
pyrrowhead/management/systemregistry.py
pyrrowhead/management/utils.py
pyrrowhead/management/cli/__init__.py
pyrrowhead/management/cli/authorization.py
pyrrowhead/management/cli/orchestration.py
pyrrowhead/management/cli/service.py
pyrrowhead/management/cli/system.py
pyrrowhead/new_certificate_generation/__init__.py
pyrrowhead/new_certificate_generation/generate_certificates.py
pyrrowhead/org/__init__.py
pyrrowhead/org/cli.py
pyrrowhead/org/initialize_org.py
pyrrowhead/templates/certificates/mk_certs.sh
pyrrowhead/templates/core_system_config/authorization.properties
pyrrowhead/templates/core_system_config/base.properties
pyrrowhead/templates/core_system_config/certificate_authority.properties
pyrrowhead/templates/core_system_config/device_registry.properties
pyrrowhead/templates/core_system_config/event_handler.properties
pyrrowhead/templates/core_system_config/gatekeeper.properties
pyrrowhead/templates/core_system_config/gateway.properties
pyrrowhead-0.5.0b0.dist-info/LICENSE.txt
pyrrowhead-0.5.0b0.dist-info/METADATA
pyrrowhead-0.5.0b0.dist-info/WHEEL
pyrrowhead-0.5.0b0.dist-info/entry_points.txt
pyrrowhead-0.5.0b0.dist-info/top_level.txt
pyrrowhead-0.5.0b0.dist-info/RECORD
