Metadata-Version: 2.1
Name: pyrrowhead
Version: 0.5.0b0
Summary: The CLI Arrowhead local cloud management tool!
Author: Jacob Nilsson
Author-email: jacob.nilsson@ltu.se
Maintainer: Jacob Nilsson
Maintainer-email: jacob.nilsson@ltu.se
License: UNKNOWN
Platform: UNKNOWN
Classifier: Development Status :: 4 - Beta
Classifier: Programming Language :: Python
Classifier: Programming Language :: Python :: 3.8
Classifier: Programming Language :: Python :: 3.9
Classifier: License :: OSI Approved :: Eclipse Public License 2.0 (EPL-2.0)
Classifier: Operating System :: POSIX :: Linux
Requires-Python: >=3.8
License-File: LICENSE.txt
Requires-Dist: pyyaml (~=5.4.1)
Requires-Dist: yamlloader (~=1.0.0)
Requires-Dist: typer (>=0.4.0)
Requires-Dist: click (>=8.0)
Requires-Dist: jinja2 (~=3.0.1)
Requires-Dist: rich (==10.*)
Requires-Dist: requests (~=2.26)
Requires-Dist: cryptography (~=35.0)
Provides-Extra: test
Requires-Dist: tox (~=3.24) ; extra == 'test'
Requires-Dist: coverage[toml] (~=6.3.2) ; extra == 'test'
Requires-Dist: pytest (~=6.2.0) ; extra == 'test'
Requires-Dist: flake8 (~=4.0.1) ; extra == 'test'
